freckle/__init__.py
freckle/__main__.py
freckle/backup.py
freckle/cli/__init__.py
freckle/cli/config.py
freckle/cli/discover.py
freckle/cli/doctor.py
freckle/cli/fetch.py
freckle/cli/files.py
freckle/cli/git.py
freckle/cli/helpers.py
freckle/cli/history.py
freckle/cli/init.py
freckle/cli/output.py
freckle/cli/profile/__init__.py
freckle/cli/profile/create.py
freckle/cli/profile/delete.py
freckle/cli/profile/helpers.py
freckle/cli/profile/operations.py
freckle/cli/push.py
freckle/cli/restore.py
freckle/cli/save.py
freckle/cli/schedule.py
freckle/cli/status.py
freckle/cli/tools.py
freckle/cli/version.py
freckle/config.py
freckle/discovery.py
freckle/dotfiles/__init__.py
freckle/dotfiles/branch.py
freckle/dotfiles/history.py
freckle/dotfiles/manager.py
freckle/dotfiles/operations.py
freckle/dotfiles/repo.py
freckle/dotfiles/types.py
freckle/secrets.py
freckle/system.py
freckle/tools_registry.py
freckle/utils.py
freckle-0.21.0.dist-info/WHEEL
freckle-0.21.0.dist-info/entry_points.txt
freckle-0.21.0.dist-info/METADATA
freckle-0.21.0.dist-info/RECORD
