Metadata-Version: 2.4
Name: freckle
Version: 0.21.0
Summary: Keep track of all your dot(file)s. A dotfiles manager with tool installation.
Keywords: dotfiles,configuration,bootstrap,setup,cli
Author: Peter Prescott
Author-email: Peter Prescott <prescott.peter@gmail.com>
License-Expression: MIT
Classifier: Development Status :: 4 - Beta
Classifier: Environment :: Console
Classifier: Intended Audience :: Developers
Classifier: License :: OSI Approved :: MIT License
Classifier: Operating System :: POSIX :: Linux
Classifier: Operating System :: MacOS
Classifier: Programming Language :: Python :: 3
Classifier: Programming Language :: Python :: 3.9
Classifier: Programming Language :: Python :: 3.10
Classifier: Programming Language :: Python :: 3.11
Classifier: Programming Language :: Python :: 3.12
Classifier: Programming Language :: Python :: 3.13
Classifier: Topic :: System :: Installation/Setup
Classifier: Topic :: System :: Systems Administration
Requires-Dist: typer>=0.15.0
Requires-Dist: pyyaml>=6.0.3
Requires-Python: >=3.9
Project-URL: Homepage, https://github.com/peterprescott/freckle
Project-URL: Repository, https://github.com/peterprescott/freckle
Project-URL: Issues, https://github.com/peterprescott/freckle/issues
